spanning_forest_builder/__init__.py
spanning_forest_builder/algorithm/Edmonds.py
spanning_forest_builder/algorithm/__init__.py
spanning_forest_builder/algorithm/algorithm.py
spanning_forest_builder/algorithm/full_search.py
spanning_forest_builder/drawing/draw_edge_labels.py
spanning_forest_builder/drawing/draw_graph.py
spanning_forest_builder-0.0.2.dist-info/METADATA
spanning_forest_builder-0.0.2.dist-info/WHEEL
spanning_forest_builder-0.0.2.dist-info/top_level.txt
spanning_forest_builder-0.0.2.dist-info/RECORD
