Metadata-Version: 2.1
Name: spanning_forest_builder
Version: 0.0.2
Summary: Build a spanning forest
Author-email: Igor Safronov <I_SIN_I@mail.ru>
Keywords: spanning forest,spanning tree
Classifier: Programming Language :: Python :: 3
Classifier: License :: OSI Approved :: MIT License
Classifier: Operating System :: OS Independent
Requires-Python: >=3.7
Requires-Dist: numpy
Requires-Dist: matplotlib
Requires-Dist: networkx
